ipyaudio/__init__.py
ipyaudio/_frontend.py
ipyaudio/_version.py
ipyaudio/player.py
ipyaudio/recorder.py
ipyaudio/timer.py
ipyaudio/utils.py
ipyaudio/widget.py
ipyaudio/configs/player.json
ipyaudio/configs/recorder.json
ipyaudio/labextension/package.json
ipyaudio/labextension/static/122.3700f0454aee82938e32.js
ipyaudio/labextension/static/270.97cadff867540e839437.js
ipyaudio/labextension/static/509.a9d6860fe38ae60aa71f.js
ipyaudio/labextension/static/570.97f2a8196b7f1703e636.js
ipyaudio/labextension/static/570.97f2a8196b7f1703e636.js.LICENSE.txt
ipyaudio/labextension/static/627.315cb148cc156382df50.js
ipyaudio/labextension/static/627.315cb148cc156382df50.js.LICENSE.txt
ipyaudio/labextension/static/style.js
ipyaudio/labextension/static/third-party-licenses.json
ipyaudio/nbextension/extension.js
ipyaudio/nbextension/index.js
ipyaudio/nbextension/index.js.LICENSE.txt
ipyaudio/nbextension/index.js.map
ipyaudio/tests/__init__.py
ipyaudio/tests/conftest.py
ipyaudio/tests/test_example.py
ipyaudio/tests/test_nbextension_path.py
ipyaudio-0.1.31.data/data/share/jupyter/labextensions/ipyaudio/package.json
ipyaudio-0.1.31.data/data/share/jupyter/labextensions/ipyaudio/static/122.3700f0454aee82938e32.js
ipyaudio-0.1.31.data/data/share/jupyter/labextensions/ipyaudio/static/270.97cadff867540e839437.js
ipyaudio-0.1.31.data/data/share/jupyter/labextensions/ipyaudio/static/509.a9d6860fe38ae60aa71f.js
ipyaudio-0.1.31.data/data/share/jupyter/labextensions/ipyaudio/static/570.97f2a8196b7f1703e636.js
ipyaudio-0.1.31.data/data/share/jupyter/labextensions/ipyaudio/static/570.97f2a8196b7f1703e636.js.LICENSE.txt
ipyaudio-0.1.31.data/data/share/jupyter/labextensions/ipyaudio/static/627.315cb148cc156382df50.js
ipyaudio-0.1.31.data/data/share/jupyter/labextensions/ipyaudio/static/627.315cb148cc156382df50.js.LICENSE.txt
ipyaudio-0.1.31.data/data/share/jupyter/labextensions/ipyaudio/static/style.js
ipyaudio-0.1.31.data/data/share/jupyter/labextensions/ipyaudio/static/third-party-licenses.json
ipyaudio-0.1.31.dist-info/METADATA
ipyaudio-0.1.31.dist-info/WHEEL
ipyaudio-0.1.31.dist-info/licenses/LICENSE.txt
ipyaudio-0.1.31.dist-info/RECORD
