Metadata-Version: 2.4
Name: ipyaudio
Version: 0.1.31
Summary: A Jupyter Widget for Web Audio Playing and Recording.
Project-URL: Homepage, https://github.com/pengzhendong/ipyaudio
Author-email: Zhendong Peng <pzd17@tsinghua.org.cn>
License: Copyright (c) 2025 Zhendong Peng
License-File: LICENSE.txt
Keywords: IPython,Jupyter,Widgets
Classifier: Framework :: Jupyter
Classifier: Intended Audience :: Developers
Classifier: Intended Audience :: Science/Research
Classifier: License :: OSI Approved :: BSD License
Classifier: Programming Language :: Python
Classifier: Programming Language :: Python :: 3
Classifier: Programming Language :: Python :: 3.7
Classifier: Programming Language :: Python :: 3.8
Classifier: Programming Language :: Python :: 3.9
Classifier: Programming Language :: Python :: 3.10
Classifier: Programming Language :: Python :: 3.11
Classifier: Programming Language :: Python :: 3.12
Requires-Python: >=3.9
Requires-Dist: audiolab>=0.2.8
Requires-Dist: ipydatawidgets>=4.3.5
Requires-Dist: ipywidgets>=8.0.0
Provides-Extra: docs
Requires-Dist: jupyter-sphinx; extra == 'docs'
Requires-Dist: nbsphinx; extra == 'docs'
Requires-Dist: nbsphinx-link; extra == 'docs'
Requires-Dist: pypandoc; extra == 'docs'
Requires-Dist: pytest-check-links; extra == 'docs'
Requires-Dist: recommonmark; extra == 'docs'
Requires-Dist: sphinx-rtd-theme; extra == 'docs'
Requires-Dist: sphinx>=1.5; extra == 'docs'
Provides-Extra: examples
Provides-Extra: test
Requires-Dist: nbval; extra == 'test'
Requires-Dist: pytest-cov; extra == 'test'
Requires-Dist: pytest>=6.0; extra == 'test'
